chanty/__init__.py
chanty/__main__.py
chanty/config.py
chanty/logging.py
chanty/utils.py
chanty/cli/__init__.py
chanty/cli/logging.py
chanty/cli/main.py
chanty/cli/utils.py
chanty/cli/commands/__init__.py
chanty/cli/commands/build.py
chanty/cli/commands/create.py
chanty/cli/commands/dev.py
chanty/cli/commands/up.py
chanty/command/__init__.py
chanty/command/builder.py
chanty/command/condition.py
chanty/command/random.py
chanty/command/scoreboard_context.py
chanty/command/selector.py
chanty/command/selector_context.py
chanty/command/types.py
chanty/types/__init__.py
chanty/types/custom_item.py
chanty/types/custom_model.py
chanty/types/entity.py
chanty/types/exceptions.py
chanty/types/items.py
chanty/types/namespace.py
chanty/types/pack_format.py
chanty/types/position.py
chanty/types/recipe.py
chanty/types/translations.py
chanty-0.4.1.dist-info/METADATA
chanty-0.4.1.dist-info/WHEEL
chanty-0.4.1.dist-info/licenses/LICENSE
chanty-0.4.1.dist-info/RECORD
