Metadata-Version: 2.4
Name: chanty
Version: 0.4.1
Summary: Tool for creating cool Minecraft datapacks
Project-URL: Homepage, https://github.com/Ethosa/chanty
Project-URL: Source, https://github.com/Ethosa/chanty
Author-email: Ethosa <social.ethosa@gmail.com>
License: MIT License
License-File: LICENSE
Keywords: automation,commands,datapack,dsl,minecraft
Requires-Python: >=3.10
